MANIFEST.in
README.rst
VERSION
setup.py
docs/Makefile
docs/changelog.rst
docs/conf.py
docs/index.rst
docs/pynsive.plugin.rst
docs/pynsive.rst
docs/usage.rst
pynsive/__init__.py
pynsive/common.py
pynsive/reflection.py
pynsive.egg-info/PKG-INFO
pynsive.egg-info/SOURCES.txt
pynsive.egg-info/dependency_links.txt
pynsive.egg-info/not-zip-safe
pynsive.egg-info/top_level.txt
pynsive/plugin/__init__.py
pynsive/plugin/loader.py
pynsive/plugin/manager.py
tests/__init__.py
tests/plugin_test.py
tools/dev-requires
tools/doc-requires
tools/install-requires
tools/test-requires