Metadata-Version: 1.1
Name: pynsive
Version: 0.2.2
Summary: A Python plugin and module introspection library.
Home-page: https://github.com/zinic/pynsive
Author: John Hopper
Author-email: john.hopper@jpserver.net
License: Apache 2.0
Download-URL: https://pypi.python.org/pypi/pynsive
Platform: UNKNOWN
Classifier: Development Status :: 4 - Beta
Classifier: License :: OSI Approved :: MIT License
Classifier: Natural Language :: English
Classifier: Environment :: Plugins
Classifier: Programming Language :: Python
Classifier: Programming Language :: Python :: Implementation :: CPython
Classifier: Programming Language :: Python :: 2.7
Classifier: Programming Language :: Python :: 3.3
